dbstorage/__init__.py
dbstorage/admin.py
dbstorage/apps.py
dbstorage/forms.py
dbstorage/models.py
dbstorage/storage.py
dbstorage/urls.py
dbstorage/views.py
dbstorage/migrations/0001_initial.py
dbstorage/migrations/__init__.py
django_db_storage-1.0.2.dist-info/DESCRIPTION.rst
django_db_storage-1.0.2.dist-info/METADATA
django_db_storage-1.0.2.dist-info/RECORD
django_db_storage-1.0.2.dist-info/WHEEL
django_db_storage-1.0.2.dist-info/metadata.json
django_db_storage-1.0.2.dist-info/top_level.txt
