Metadata-Version: 2.0
Name: django-db-storage
Version: 1.0.2
Summary: Custom Database Storage for Django
Home-page: https://github.com/derekkwok/django-db-storage
Author: Derek Kwok
Author-email: derek.kai.chun.kwok@gmail.com
License: BSD
Keywords: django metrics analytics
Platform: UNKNOWN
Classifier: Development Status :: 5 - Production/Stable
Classifier: Environment :: Web Environment
Classifier: Intended Audience :: Developers
Classifier: License :: OSI Approved :: BSD License
Classifier: Operating System :: OS Independent
Classifier: Programming Language :: Python :: 2
Classifier: Programming Language :: Python :: 2.7
Classifier: Programming Language :: Python :: 3
Classifier: Programming Language :: Python :: 3.4
Classifier: Programming Language :: Python :: 3.5
Classifier: Topic :: Internet :: WWW/HTTP :: Dynamic Content
Classifier: Topic :: Software Development :: Libraries :: Python Modules
